xetcache/__init__.py
xetcache/config.py
xetcache/util.py
xetcache/xetmemo_kernel_extension.py
xetcache-0.0.2.dist-info/LICENSE
xetcache-0.0.2.dist-info/METADATA
xetcache-0.0.2.dist-info/WHEEL
xetcache-0.0.2.dist-info/top_level.txt
xetcache-0.0.2.dist-info/RECORD
