Metadata-Version: 2.1
Name: xetcache
Version: 0.0.2
Summary: An extension for IPython that help to run AsyncIO code in your interactive session.
Home-page: https://github.com/xetdata/xetcache
Author: Yucheng Low
Author-email: ylow@xethub.com
Classifier: Development Status :: 3 - Alpha
Classifier: Framework :: IPython
Classifier: Intended Audience :: Developers
Classifier: Operating System :: OS Independent
Classifier: Programming Language :: Python
Classifier: Programming Language :: Python :: 3
Classifier: Programming Language :: Python :: 3.6
Classifier: Programming Language :: Python :: 3.7
Classifier: Programming Language :: Python :: 3.8
Classifier: Programming Language :: Python :: 3.9
Classifier: Programming Language :: Python :: 3.10
Classifier: Programming Language :: Python :: 3.11
Classifier: Topic :: Software Development :: Libraries :: Python Modules
License-File: LICENSE
Requires-Dist: ipython
Requires-Dist: pyxet
Requires-Dist: fsspec
